mkdocs_svg_to_png/__init__.py
mkdocs_svg_to_png/_version.py
mkdocs_svg_to_png/config.py
mkdocs_svg_to_png/exceptions.py
mkdocs_svg_to_png/logging_config.py
mkdocs_svg_to_png/markdown_processor.py
mkdocs_svg_to_png/plugin.py
mkdocs_svg_to_png/processor.py
mkdocs_svg_to_png/svg_block.py
mkdocs_svg_to_png/svg_converter.py
mkdocs_svg_to_png/types.py
mkdocs_svg_to_png/utils.py
mkdocs_svg_to_png-0.0.9.dist-info/METADATA
mkdocs_svg_to_png-0.0.9.dist-info/WHEEL
mkdocs_svg_to_png-0.0.9.dist-info/entry_points.txt
mkdocs_svg_to_png-0.0.9.dist-info/licenses/LICENSE
mkdocs_svg_to_png-0.0.9.dist-info/licenses/LICENSE copy
mkdocs_svg_to_png-0.0.9.dist-info/RECORD
